df_auth/__init__.py
df_auth/admin.py
df_auth/apps.py
df_auth/backends.py
df_auth/defaults.py
df_auth/exceptions.py
df_auth/managers.py
df_auth/models.py
df_auth/permissions.py
df_auth/remote_config.py
df_auth/settings.py
df_auth/strategy.py
df_auth/utils.py
df_auth/drf/__init__.py
df_auth/drf/serializers.py
df_auth/drf/urls.py
df_auth/drf/viewsets.py
df_auth/migrations/0001_initial.py
df_auth/migrations/0002_alter_user2fa_user_userregistration.py
df_auth/migrations/0003_alter_userregistration_is_registering.py
df_auth/migrations/__init__.py
df_auth/templatetags/__init__.py
df_auth/templatetags/auth_magic_link.py
django_df_auth-1.0.11.dist-info/LICENSE
django_df_auth-1.0.11.dist-info/METADATA
django_df_auth-1.0.11.dist-info/WHEEL
django_df_auth-1.0.11.dist-info/top_level.txt
django_df_auth-1.0.11.dist-info/RECORD
